dbt/__init__.py
dbt/adapters/__init__.py
dbt/adapters/sas/__init__.py
dbt/adapters/sas/__version__.py
dbt/adapters/sas/column.py
dbt/adapters/sas/connections.py
dbt/adapters/sas/constants.py
dbt/adapters/sas/credentials.py
dbt/adapters/sas/cte.py
dbt/adapters/sas/impl.py
dbt/adapters/sas/relation.py
dbt/adapters/sas/sas_log.py
dbt/adapters/sas/sas_macros.py
dbt/adapters/sas/utils.py
dbt/adapters/sas/whereis.py
dbt/adapters/sas/code/assign_libnames.sas
dbt/adapters/sas/code/columns_equal.sql
dbt/adapters/sas/code/create_schema.sas
dbt/adapters/sas/code/delete_data_set.sas
dbt/adapters/sas/code/delete_file.sas
dbt/adapters/sas/code/drop_schema.sas
dbt/adapters/sas/code/import_csv.sas
dbt/adapters/sas/code/noop.sas
dbt/adapters/sas/code/proc_sql.sas
dbt/adapters/sas/code/proc_sql_select.sas
dbt/adapters/sas/code/rename_data_set.sas
dbt/adapters/sas/code/truncate_data_set.sas
dbt/adapters/sas/code/upload_file.sas
dbt/adapters/sas/handlers/__init__.py
dbt/adapters/sas/handlers/abstract_handler.py
dbt/adapters/sas/handlers/saspy_handler.py
dbt/adapters/sas/handlers/ws_handler.py
dbt/include/__init__.py
dbt/include/sas/__init__.py
dbt/include/sas/dbt_project.yml
dbt/include/sas/profile_template.yml
dbt/include/sas/macros/adapters.sql
dbt/include/sas/macros/catalog.sql
dbt/include/sas/macros/materializations/models/table/create_table_as.sql
dbt/include/sas/macros/materializations/seeds/helpers.sql
dbt/include/sas/macros/materializations/tests/helpers.sql
dbt/include/sas/macros/utils/cast_bool_to_text.sql
dbt_sas-1.3.0a17.dist-info/METADATA
dbt_sas-1.3.0a17.dist-info/WHEEL
dbt_sas-1.3.0a17.dist-info/top_level.txt
dbt_sas-1.3.0a17.dist-info/RECORD
