Metadata-Version: 2.1
Name: dbt-sas
Version: 1.3.0a17
Summary: dbt (data build tool) adapter for SAS
Home-page: https://github.com/DLBD-Department/dbt-sas
Author: Alkemy Spa
Author-email: DLBDDepartment@nunatac.it
License: Apache License 2.0
Project-URL: Bug Tracker, https://github.com/DLBD-Department/dbt-sas/issues
Project-URL: Source Code, https://github.com/DLBD-Department/dbt-sas
Keywords: dbt,sas
Platform: any
Classifier: Development Status :: 5 - Production/Stable
Classifier: Environment :: Console
Classifier: Intended Audience :: Developers
Classifier: License :: OSI Approved :: Apache Software License
Classifier: Operating System :: OS Independent
Classifier: Programming Language :: Python
Classifier: Topic :: Software Development :: Libraries :: Python Modules
Classifier: Programming Language :: Python :: 3.6
Classifier: Programming Language :: Python :: 3.7
Classifier: Programming Language :: Python :: 3.8
Classifier: Programming Language :: Python :: 3.9
Classifier: Programming Language :: Python :: 3.10
Classifier: Programming Language :: Python :: 3.11
Requires-Python: >=3.6
Provides-Extra: test
Requires-Dist: pytest ; extra == 'test'
